Metadata-Version: 2.1
Name: twitch-plays-hackru
Version: 1.1.0
Summary: A TwitchPlays API
Home-page: https://github.com/HackRU/twitch-plays
Author: Jeffrey Fung
Author-email: rnd@hackru.org
License: UNKNOWN
Platform: UNKNOWN
Classifier: Programming Language :: Python :: 3
Classifier: License :: OSI Approved :: GNU General Public License v3 (GPLv3)
Classifier: Operating System :: OS Independent
Requires-Python: >=3.6
